{
  "username": "adrielvieira10",
  "imageUrl": "blob:null/f4c99462-34ea-42c8-ae47-16f2ac60a819",
  "totalParticipacoes": 8,
  "totalEliminacoes": 3,
  "pontosAcumulados": 36,
  "mediaRank": "2573.38",
  "mediaEliminacoes": "0.38",
  "melhorRank": {
    "rank": 168,
    "date": "2025-10-20"
  },
  "piorRank": {
    "rank": 4447,
    "date": "2025-10-17"
  },
  "historicoDeBatalhas": [
    {
      "date": "2025-10-14",
      "rank": 1575,
      "pontos": 5,
      "eliminatedCount": 0
    },
    {
      "date": "2025-10-15",
      "rank": 2754,
      "pontos": 3,
      "eliminatedCount": 0,
      "eliminatedBy": "souodac"
    },
    {
      "date": "2025-10-16",
      "rank": 2954,
      "pontos": 3,
      "eliminatedCount": 0,
      "eliminatedBy": "loweslley"
    },
    {
      "date": "2025-10-17",
      "rank": 4447,
      "pontos": 0,
      "eliminatedCount": 0,
      "eliminatedBy": "gui.cs7"
    },
    {
      "date": "2025-10-18",
      "rank": 3342,
      "pontos": 1,
      "eliminatedCount": 0,
      "eliminatedBy": "hiago_storm_rain"
    },
    {
      "date": "2025-10-19",
      "rank": 2197,
      "pontos": 3,
      "eliminatedCount": 0,
      "eliminatedBy": "Desconhecido"
    },
    {
      "date": "2025-10-20",
      "rank": 168,
      "pontos": 20,
      "eliminatedCount": 3,
      "eliminatedBy": "flavin_xt7"
    },
    {
      "date": "2025-10-21",
      "rank": 3150,
      "pontos": 1,
      "eliminatedCount": 0,
      "eliminatedBy": "mr_unknowdsbm"
    }
  ]
}