{
  "username": "anapaula2256",
  "imageUrl": "blob:null/3cdc7a4e-3cfb-4302-af2a-b3cfd20fce99",
  "totalParticipacoes": 9,
  "totalEliminacoes": 7,
  "pontosAcumulados": 54,
  "mediaRank": "2157.78",
  "mediaEliminacoes": "0.78",
  "melhorRank": {
    "rank": 284,
    "date": "2025-10-17"
  },
  "piorRank": {
    "rank": 3797,
    "date": "2025-10-16"
  },
  "historicoDeBatalhas": [
    {
      "date": "2025-10-13",
      "rank": 822,
      "pontos": 10,
      "eliminatedCount": 0
    },
    {
      "date": "2025-10-14",
      "rank": 3695,
      "pontos": 1,
      "eliminatedCount": 0
    },
    {
      "date": "2025-10-15",
      "rank": 3383,
      "pontos": 1,
      "eliminatedCount": 2,
      "eliminatedBy": "_huguinho_001_"
    },
    {
      "date": "2025-10-16",
      "rank": 3797,
      "pontos": 1,
      "eliminatedCount": 1,
      "eliminatedBy": "vanessaferreira6601"
    },
    {
      "date": "2025-10-17",
      "rank": 284,
      "pontos": 15,
      "eliminatedCount": 2,
      "eliminatedBy": "ae_kauan_05"
    },
    {
      "date": "2025-10-18",
      "rank": 1851,
      "pontos": 5,
      "eliminatedCount": 0,
      "eliminatedBy": "barbosax_._"
    },
    {
      "date": "2025-10-19",
      "rank": 398,
      "pontos": 15,
      "eliminatedCount": 0,
      "eliminatedBy": "Desconhecido"
    },
    {
      "date": "2025-10-20",
      "rank": 3466,
      "pontos": 1,
      "eliminatedCount": 0,
      "eliminatedBy": "_milena.silva.1"
    },
    {
      "date": "2025-10-21",
      "rank": 1724,
      "pontos": 5,
      "eliminatedCount": 2,
      "eliminatedBy": "ariel.santx_"
    }
  ]
}