{
  "username": "batmanzsss",
  "imageUrl": "blob:null/88d347bb-a3b5-482f-a75c-53a9ff3643df",
  "totalParticipacoes": 9,
  "totalEliminacoes": 7,
  "pontosAcumulados": 44,
  "mediaRank": "2250.89",
  "mediaEliminacoes": "0.78",
  "melhorRank": {
    "rank": 439,
    "date": "2025-10-14"
  },
  "piorRank": {
    "rank": 3744,
    "date": "2025-10-21"
  },
  "historicoDeBatalhas": [
    {
      "date": "2025-10-13",
      "rank": 1703,
      "pontos": 5,
      "eliminatedCount": 0
    },
    {
      "date": "2025-10-14",
      "rank": 439,
      "pontos": 15,
      "eliminatedCount": 0
    },
    {
      "date": "2025-10-15",
      "rank": 976,
      "pontos": 10,
      "eliminatedCount": 2,
      "eliminatedBy": "evillynparede"
    },
    {
      "date": "2025-10-16",
      "rank": 3428,
      "pontos": 1,
      "eliminatedCount": 0,
      "eliminatedBy": "sophiaa_2806"
    },
    {
      "date": "2025-10-17",
      "rank": 2750,
      "pontos": 3,
      "eliminatedCount": 2,
      "eliminatedBy": "mohbordignon"
    },
    {
      "date": "2025-10-18",
      "rank": 1799,
      "pontos": 5,
      "eliminatedCount": 0,
      "eliminatedBy": "samuk.a133"
    },
    {
      "date": "2025-10-19",
      "rank": 2105,
      "pontos": 3,
      "eliminatedCount": 0,
      "eliminatedBy": "Desconhecido"
    },
    {
      "date": "2025-10-20",
      "rank": 3314,
      "pontos": 1,
      "eliminatedCount": 0,
      "eliminatedBy": "soso_fofa01"
    },
    {
      "date": "2025-10-21",
      "rank": 3744,
      "pontos": 1,
      "eliminatedCount": 3,
      "eliminatedBy": "madsonnfiuza"
    }
  ]
}