{
  "username": "djmarcws",
  "imageUrl": "blob:null/3598688c-93bf-4900-88c7-0cb6ed5b2168",
  "totalParticipacoes": 9,
  "totalEliminacoes": 4,
  "pontosAcumulados": 30,
  "mediaRank": "2624.56",
  "mediaEliminacoes": "0.44",
  "melhorRank": {
    "rank": 593,
    "date": "2025-10-13"
  },
  "piorRank": {
    "rank": 4275,
    "date": "2025-10-15"
  },
  "historicoDeBatalhas": [
    {
      "date": "2025-10-13",
      "rank": 593,
      "pontos": 10,
      "eliminatedCount": 0
    },
    {
      "date": "2025-10-14",
      "rank": 1982,
      "pontos": 5,
      "eliminatedCount": 0
    },
    {
      "date": "2025-10-15",
      "rank": 4275,
      "pontos": 0,
      "eliminatedCount": 0,
      "eliminatedBy": "breno_de_sousa_santos"
    },
    {
      "date": "2025-10-16",
      "rank": 3329,
      "pontos": 1,
      "eliminatedCount": 1,
      "eliminatedBy": "labarcapsul"
    },
    {
      "date": "2025-10-17",
      "rank": 2618,
      "pontos": 3,
      "eliminatedCount": 0,
      "eliminatedBy": "eowesl3y"
    },
    {
      "date": "2025-10-18",
      "rank": 2422,
      "pontos": 3,
      "eliminatedCount": 2,
      "eliminatedBy": "daviking_46"
    },
    {
      "date": "2025-10-19",
      "rank": 1959,
      "pontos": 5,
      "eliminatedCount": 0,
      "eliminatedBy": "Desconhecido"
    },
    {
      "date": "2025-10-20",
      "rank": 2350,
      "pontos": 3,
      "eliminatedCount": 1,
      "eliminatedBy": "adilene_pitucha"
    },
    {
      "date": "2025-10-21",
      "rank": 4093,
      "pontos": 0,
      "eliminatedCount": 0,
      "eliminatedBy": "ericlc193"
    }
  ]
}