{
  "username": "gersonh678",
  "imageUrl": "blob:null/7dbe80e4-54d8-40a9-a758-4180260e98a5",
  "totalParticipacoes": 9,
  "totalEliminacoes": 4,
  "pontosAcumulados": 30,
  "mediaRank": "2442.00",
  "mediaEliminacoes": "0.44",
  "melhorRank": {
    "rank": 1388,
    "date": "2025-10-20"
  },
  "piorRank": {
    "rank": 4389,
    "date": "2025-10-18"
  },
  "historicoDeBatalhas": [
    {
      "date": "2025-10-13",
      "rank": 1482,
      "pontos": 5,
      "eliminatedCount": 0
    },
    {
      "date": "2025-10-14",
      "rank": 1833,
      "pontos": 5,
      "eliminatedCount": 0
    },
    {
      "date": "2025-10-15",
      "rank": 2618,
      "pontos": 3,
      "eliminatedCount": 1,
      "eliminatedBy": "cle_coelho_mr"
    },
    {
      "date": "2025-10-16",
      "rank": 1403,
      "pontos": 5,
      "eliminatedCount": 2,
      "eliminatedBy": "karinagomescarmo2016"
    },
    {
      "date": "2025-10-17",
      "rank": 3274,
      "pontos": 1,
      "eliminatedCount": 0,
      "eliminatedBy": "lipe.sp12"
    },
    {
      "date": "2025-10-18",
      "rank": 4389,
      "pontos": 0,
      "eliminatedCount": 0,
      "eliminatedBy": "fl4vin_"
    },
    {
      "date": "2025-10-19",
      "rank": 2774,
      "pontos": 3,
      "eliminatedCount": 0,
      "eliminatedBy": "Desconhecido"
    },
    {
      "date": "2025-10-20",
      "rank": 1388,
      "pontos": 5,
      "eliminatedCount": 0,
      "eliminatedBy": "dantas0308"
    },
    {
      "date": "2025-10-21",
      "rank": 2817,
      "pontos": 3,
      "eliminatedCount": 1,
      "eliminatedBy": "jhennifersh_"
    }
  ]
}