{
  "username": "heitoroli.veira",
  "imageUrl": "blob:null/7fd5266d-7be6-435c-9d69-73551b8dcf7f",
  "totalParticipacoes": 9,
  "totalEliminacoes": 6,
  "pontosAcumulados": 20,
  "mediaRank": "2813.78",
  "mediaEliminacoes": "0.67",
  "melhorRank": {
    "rank": 1816,
    "date": "2025-10-14"
  },
  "piorRank": {
    "rank": 4529,
    "date": "2025-10-18"
  },
  "historicoDeBatalhas": [
    {
      "date": "2025-10-13",
      "rank": 2334,
      "pontos": 3,
      "eliminatedCount": 0
    },
    {
      "date": "2025-10-14",
      "rank": 1816,
      "pontos": 5,
      "eliminatedCount": 0
    },
    {
      "date": "2025-10-15",
      "rank": 2437,
      "pontos": 3,
      "eliminatedCount": 1,
      "eliminatedBy": "pvd_isawu"
    },
    {
      "date": "2025-10-16",
      "rank": 2222,
      "pontos": 3,
      "eliminatedCount": 1,
      "eliminatedBy": "elisabetesantos313"
    },
    {
      "date": "2025-10-17",
      "rank": 3248,
      "pontos": 1,
      "eliminatedCount": 2,
      "eliminatedBy": "thaylon_pires09"
    },
    {
      "date": "2025-10-18",
      "rank": 4529,
      "pontos": 0,
      "eliminatedCount": 0,
      "eliminatedBy": "hevan_araujooliveira07"
    },
    {
      "date": "2025-10-19",
      "rank": 3636,
      "pontos": 1,
      "eliminatedCount": 0,
      "eliminatedBy": "Desconhecido"
    },
    {
      "date": "2025-10-20",
      "rank": 3072,
      "pontos": 1,
      "eliminatedCount": 0,
      "eliminatedBy": "ele_andrey13"
    },
    {
      "date": "2025-10-21",
      "rank": 2030,
      "pontos": 3,
      "eliminatedCount": 2,
      "eliminatedBy": "macilo1929"
    }
  ]
}