{
  "username": "izabelle_cristina777",
  "imageUrl": "blob:null/e7e10682-ed0d-4337-8bd3-0fedc23a40e8",
  "totalParticipacoes": 8,
  "totalEliminacoes": 3,
  "pontosAcumulados": 46,
  "mediaRank": "1863.13",
  "mediaEliminacoes": "0.38",
  "melhorRank": {
    "rank": 398,
    "date": "2025-10-17"
  },
  "piorRank": {
    "rank": 4229,
    "date": "2025-10-20"
  },
  "historicoDeBatalhas": [
    {
      "date": "2025-10-14",
      "rank": 1783,
      "pontos": 5,
      "eliminatedCount": 0
    },
    {
      "date": "2025-10-15",
      "rank": 3653,
      "pontos": 1,
      "eliminatedCount": 0,
      "eliminatedBy": "david_matheus_oliveira_bastos"
    },
    {
      "date": "2025-10-16",
      "rank": 1079,
      "pontos": 5,
      "eliminatedCount": 1,
      "eliminatedBy": "suelenoliveira89"
    },
    {
      "date": "2025-10-17",
      "rank": 398,
      "pontos": 15,
      "eliminatedCount": 1,
      "eliminatedBy": "instakellinton"
    },
    {
      "date": "2025-10-18",
      "rank": 1555,
      "pontos": 5,
      "eliminatedCount": 1,
      "eliminatedBy": "wesleyturockcavalcante"
    },
    {
      "date": "2025-10-19",
      "rank": 702,
      "pontos": 10,
      "eliminatedCount": 0,
      "eliminatedBy": "Desconhecido"
    },
    {
      "date": "2025-10-20",
      "rank": 4229,
      "pontos": 0,
      "eliminatedCount": 0,
      "eliminatedBy": "hiago_storm_rain"
    },
    {
      "date": "2025-10-21",
      "rank": 1506,
      "pontos": 5,
      "eliminatedCount": 0,
      "eliminatedBy": "gleison520"
    }
  ]
}