{
  "username": "jaoz.inw",
  "imageUrl": "blob:null/b476e8a8-8ba1-4531-b5a1-d0e80876e0b5",
  "totalParticipacoes": 9,
  "totalEliminacoes": 7,
  "pontosAcumulados": 44,
  "mediaRank": "2215.89",
  "mediaEliminacoes": "0.78",
  "melhorRank": {
    "rank": 479,
    "date": "2025-10-20"
  },
  "piorRank": {
    "rank": 3631,
    "date": "2025-10-16"
  },
  "historicoDeBatalhas": [
    {
      "date": "2025-10-13",
      "rank": 1275,
      "pontos": 5,
      "eliminatedCount": 0
    },
    {
      "date": "2025-10-14",
      "rank": 3508,
      "pontos": 1,
      "eliminatedCount": 0
    },
    {
      "date": "2025-10-15",
      "rank": 2404,
      "pontos": 3,
      "eliminatedCount": 0,
      "eliminatedBy": "janainanascimento132"
    },
    {
      "date": "2025-10-16",
      "rank": 3631,
      "pontos": 1,
      "eliminatedCount": 1,
      "eliminatedBy": "yan.fxp77"
    },
    {
      "date": "2025-10-17",
      "rank": 885,
      "pontos": 10,
      "eliminatedCount": 2,
      "eliminatedBy": "pedro_mariano_bjj"
    },
    {
      "date": "2025-10-18",
      "rank": 2939,
      "pontos": 3,
      "eliminatedCount": 1,
      "eliminatedBy": "jotafx.gotizy"
    },
    {
      "date": "2025-10-19",
      "rank": 2630,
      "pontos": 3,
      "eliminatedCount": 0,
      "eliminatedBy": "Desconhecido"
    },
    {
      "date": "2025-10-20",
      "rank": 479,
      "pontos": 15,
      "eliminatedCount": 1,
      "eliminatedBy": "mendes05._"
    },
    {
      "date": "2025-10-21",
      "rank": 2192,
      "pontos": 3,
      "eliminatedCount": 2,
      "eliminatedBy": "danillor_fs"
    }
  ]
}