{
  "username": "jun10r_eduardo",
  "imageUrl": "blob:null/a6fb4cca-0efc-434b-b662-78880404080b",
  "totalParticipacoes": 8,
  "totalEliminacoes": 6,
  "pontosAcumulados": 37,
  "mediaRank": "2849.38",
  "mediaEliminacoes": "0.75",
  "melhorRank": {
    "rank": 248,
    "date": "2025-10-15"
  },
  "piorRank": {
    "rank": 4207,
    "date": "2025-10-16"
  },
  "historicoDeBatalhas": [
    {
      "date": "2025-10-14",
      "rank": 4103,
      "pontos": 0,
      "eliminatedCount": 0
    },
    {
      "date": "2025-10-15",
      "rank": 248,
      "pontos": 20,
      "eliminatedCount": 5,
      "eliminatedBy": "tulio_casagrande"
    },
    {
      "date": "2025-10-16",
      "rank": 4207,
      "pontos": 0,
      "eliminatedCount": 1,
      "eliminatedBy": "alinesereya"
    },
    {
      "date": "2025-10-17",
      "rank": 2853,
      "pontos": 3,
      "eliminatedCount": 0,
      "eliminatedBy": "1507_oliveiraxx"
    },
    {
      "date": "2025-10-18",
      "rank": 4156,
      "pontos": 0,
      "eliminatedCount": 0,
      "eliminatedBy": "jazin_pvp"
    },
    {
      "date": "2025-10-19",
      "rank": 3558,
      "pontos": 1,
      "eliminatedCount": 0,
      "eliminatedBy": "Desconhecido"
    },
    {
      "date": "2025-10-20",
      "rank": 2846,
      "pontos": 3,
      "eliminatedCount": 0,
      "eliminatedBy": "iam_thomaz._"
    },
    {
      "date": "2025-10-21",
      "rank": 824,
      "pontos": 10,
      "eliminatedCount": 0,
      "eliminatedBy": "gustav0_gb_0ficial"
    }
  ]
}