{
  "username": "khalillj077",
  "imageUrl": "blob:null/ca43d9d5-e79a-4bd1-a26b-de142d5bfdcb",
  "totalParticipacoes": 9,
  "totalEliminacoes": 1,
  "pontosAcumulados": 43,
  "mediaRank": "2363.33",
  "mediaEliminacoes": "0.11",
  "melhorRank": {
    "rank": 231,
    "date": "2025-10-18"
  },
  "piorRank": {
    "rank": 4059,
    "date": "2025-10-16"
  },
  "historicoDeBatalhas": [
    {
      "date": "2025-10-13",
      "rank": 2174,
      "pontos": 3,
      "eliminatedCount": 0
    },
    {
      "date": "2025-10-14",
      "rank": 3979,
      "pontos": 1,
      "eliminatedCount": 0
    },
    {
      "date": "2025-10-15",
      "rank": 3241,
      "pontos": 1,
      "eliminatedCount": 0,
      "eliminatedBy": "braia2k25"
    },
    {
      "date": "2025-10-16",
      "rank": 4059,
      "pontos": 0,
      "eliminatedCount": 0,
      "eliminatedBy": "pedroelias_2013"
    },
    {
      "date": "2025-10-17",
      "rank": 1739,
      "pontos": 5,
      "eliminatedCount": 1,
      "eliminatedBy": "guizinggf"
    },
    {
      "date": "2025-10-18",
      "rank": 231,
      "pontos": 20,
      "eliminatedCount": 0,
      "eliminatedBy": "pvd_santzbia"
    },
    {
      "date": "2025-10-19",
      "rank": 1679,
      "pontos": 5,
      "eliminatedCount": 0,
      "eliminatedBy": "Desconhecido"
    },
    {
      "date": "2025-10-20",
      "rank": 1986,
      "pontos": 5,
      "eliminatedCount": 0,
      "eliminatedBy": "gettjinx3d"
    },
    {
      "date": "2025-10-21",
      "rank": 2182,
      "pontos": 3,
      "eliminatedCount": 0,
      "eliminatedBy": "daviluiz.lacerda"
    }
  ]
}