{
  "username": "l.gomes_91",
  "imageUrl": "blob:null/0f231f6e-023b-4c53-91d6-9f1850c44e5f",
  "totalParticipacoes": 9,
  "totalEliminacoes": 8,
  "pontosAcumulados": 55,
  "mediaRank": "1927.67",
  "mediaEliminacoes": "0.89",
  "melhorRank": {
    "rank": 317,
    "date": "2025-10-18"
  },
  "piorRank": {
    "rank": 4408,
    "date": "2025-10-17"
  },
  "historicoDeBatalhas": [
    {
      "date": "2025-10-13",
      "rank": 843,
      "pontos": 10,
      "eliminatedCount": 0
    },
    {
      "date": "2025-10-14",
      "rank": 2251,
      "pontos": 3,
      "eliminatedCount": 0
    },
    {
      "date": "2025-10-15",
      "rank": 633,
      "pontos": 10,
      "eliminatedCount": 1,
      "eliminatedBy": "lulinhadiny"
    },
    {
      "date": "2025-10-16",
      "rank": 2059,
      "pontos": 3,
      "eliminatedCount": 1,
      "eliminatedBy": "oh.jhonn"
    },
    {
      "date": "2025-10-17",
      "rank": 4408,
      "pontos": 0,
      "eliminatedCount": 1,
      "eliminatedBy": "fl4vio.007"
    },
    {
      "date": "2025-10-18",
      "rank": 317,
      "pontos": 15,
      "eliminatedCount": 4,
      "eliminatedBy": "nandinho.cris"
    },
    {
      "date": "2025-10-19",
      "rank": 3532,
      "pontos": 1,
      "eliminatedCount": 0,
      "eliminatedBy": "Desconhecido"
    },
    {
      "date": "2025-10-20",
      "rank": 2700,
      "pontos": 3,
      "eliminatedCount": 1,
      "eliminatedBy": "min_.yuka"
    },
    {
      "date": "2025-10-21",
      "rank": 606,
      "pontos": 10,
      "eliminatedCount": 0,
      "eliminatedBy": "lucasshelbys"
    }
  ]
}