{
  "username": "luca_.leao",
  "imageUrl": "blob:null/a1e1fdc1-240e-489c-99f1-10c2747790b8",
  "totalParticipacoes": 9,
  "totalEliminacoes": 5,
  "pontosAcumulados": 57,
  "mediaRank": "2227.56",
  "mediaEliminacoes": "0.56",
  "melhorRank": {
    "rank": 94,
    "date": "2025-10-16"
  },
  "piorRank": {
    "rank": 3937,
    "date": "2025-10-21"
  },
  "historicoDeBatalhas": [
    {
      "date": "2025-10-13",
      "rank": 2160,
      "pontos": 3,
      "eliminatedCount": 0
    },
    {
      "date": "2025-10-14",
      "rank": 2234,
      "pontos": 3,
      "eliminatedCount": 0
    },
    {
      "date": "2025-10-15",
      "rank": 3497,
      "pontos": 1,
      "eliminatedCount": 0,
      "eliminatedBy": "lucaaswzl"
    },
    {
      "date": "2025-10-16",
      "rank": 94,
      "pontos": 30,
      "eliminatedCount": 4,
      "eliminatedBy": "ezra_gabriel25"
    },
    {
      "date": "2025-10-17",
      "rank": 2543,
      "pontos": 3,
      "eliminatedCount": 0,
      "eliminatedBy": "eu_silvahbk"
    },
    {
      "date": "2025-10-18",
      "rank": 3570,
      "pontos": 1,
      "eliminatedCount": 0,
      "eliminatedBy": "lucas.gabriel9.8"
    },
    {
      "date": "2025-10-19",
      "rank": 598,
      "pontos": 10,
      "eliminatedCount": 0,
      "eliminatedBy": "Desconhecido"
    },
    {
      "date": "2025-10-20",
      "rank": 1415,
      "pontos": 5,
      "eliminatedCount": 1,
      "eliminatedBy": "chaga___off"
    },
    {
      "date": "2025-10-21",
      "rank": 3937,
      "pontos": 1,
      "eliminatedCount": 0,
      "eliminatedBy": "yara_alice"
    }
  ]
}