{
  "username": "madsonnfiuza",
  "imageUrl": "blob:null/bcd66947-9fdb-4a76-b2a7-78f744109c08",
  "totalParticipacoes": 9,
  "totalEliminacoes": 6,
  "pontosAcumulados": 64,
  "mediaRank": "2128.44",
  "mediaEliminacoes": "0.67",
  "melhorRank": {
    "rank": 235,
    "date": "2025-10-14"
  },
  "piorRank": {
    "rank": 3819,
    "date": "2025-10-15"
  },
  "historicoDeBatalhas": [
    {
      "date": "2025-10-13",
      "rank": 2520,
      "pontos": 3,
      "eliminatedCount": 0
    },
    {
      "date": "2025-10-14",
      "rank": 235,
      "pontos": 20,
      "eliminatedCount": 0
    },
    {
      "date": "2025-10-15",
      "rank": 3819,
      "pontos": 1,
      "eliminatedCount": 0,
      "eliminatedBy": "luccayan456"
    },
    {
      "date": "2025-10-16",
      "rank": 1636,
      "pontos": 5,
      "eliminatedCount": 1,
      "eliminatedBy": "leticia_barboza19"
    },
    {
      "date": "2025-10-17",
      "rank": 317,
      "pontos": 15,
      "eliminatedCount": 1,
      "eliminatedBy": "ederalex_"
    },
    {
      "date": "2025-10-18",
      "rank": 2826,
      "pontos": 3,
      "eliminatedCount": 1,
      "eliminatedBy": "oh.jhonn"
    },
    {
      "date": "2025-10-19",
      "rank": 310,
      "pontos": 15,
      "eliminatedCount": 0,
      "eliminatedBy": "Desconhecido"
    },
    {
      "date": "2025-10-20",
      "rank": 3750,
      "pontos": 1,
      "eliminatedCount": 2,
      "eliminatedBy": "ikaru0011"
    },
    {
      "date": "2025-10-21",
      "rank": 3743,
      "pontos": 1,
      "eliminatedCount": 1,
      "eliminatedBy": "batmanzsss"
    }
  ]
}