{
  "username": "mello_kaua_2025",
  "imageUrl": "blob:null/d38c7e19-eeb1-4322-85be-66ae5bf1f060",
  "totalParticipacoes": 3,
  "totalEliminacoes": 4,
  "pontosAcumulados": 28,
  "mediaRank": "1247.67",
  "mediaEliminacoes": "1.33",
  "melhorRank": {
    "rank": 188,
    "date": "2025-10-20"
  },
  "piorRank": {
    "rank": 2424,
    "date": "2025-10-19"
  },
  "historicoDeBatalhas": [
    {
      "date": "2025-10-19",
      "rank": 2424,
      "pontos": 3,
      "eliminatedCount": 0,
      "eliminatedBy": "Desconhecido"
    },
    {
      "date": "2025-10-20",
      "rank": 188,
      "pontos": 20,
      "eliminatedCount": 3,
      "eliminatedBy": "ketilynvitoria_d"
    },
    {
      "date": "2025-10-21",
      "rank": 1131,
      "pontos": 5,
      "eliminatedCount": 1,
      "eliminatedBy": "thommes_244_"
    }
  ]
}