{
  "username": "miguel.calleb.58",
  "imageUrl": "blob:null/be303191-f0b2-4dea-9465-b97bfd7c42d3",
  "totalParticipacoes": 9,
  "totalEliminacoes": 4,
  "pontosAcumulados": 61,
  "mediaRank": "1453.00",
  "mediaEliminacoes": "0.44",
  "melhorRank": {
    "rank": 332,
    "date": "2025-10-15"
  },
  "piorRank": {
    "rank": 2865,
    "date": "2025-10-20"
  },
  "historicoDeBatalhas": [
    {
      "date": "2025-10-13",
      "rank": 1865,
      "pontos": 5,
      "eliminatedCount": 0
    },
    {
      "date": "2025-10-14",
      "rank": 732,
      "pontos": 10,
      "eliminatedCount": 0
    },
    {
      "date": "2025-10-15",
      "rank": 332,
      "pontos": 15,
      "eliminatedCount": 2,
      "eliminatedBy": "kaua.santoz"
    },
    {
      "date": "2025-10-16",
      "rank": 1368,
      "pontos": 5,
      "eliminatedCount": 0,
      "eliminatedBy": "kaine.xavier"
    },
    {
      "date": "2025-10-17",
      "rank": 1579,
      "pontos": 5,
      "eliminatedCount": 0,
      "eliminatedBy": "wails_mxria"
    },
    {
      "date": "2025-10-18",
      "rank": 1023,
      "pontos": 5,
      "eliminatedCount": 2,
      "eliminatedBy": "carl27070"
    },
    {
      "date": "2025-10-19",
      "rank": 2791,
      "pontos": 3,
      "eliminatedCount": 0,
      "eliminatedBy": "Desconhecido"
    },
    {
      "date": "2025-10-20",
      "rank": 2865,
      "pontos": 3,
      "eliminatedCount": 0,
      "eliminatedBy": "henriquecaetanobsb"
    },
    {
      "date": "2025-10-21",
      "rank": 522,
      "pontos": 10,
      "eliminatedCount": 0,
      "eliminatedBy": "eae_mano_jeff19"
    }
  ]
}