{
  "username": "miguel_isaiass",
  "imageUrl": "blob:null/a89dff16-8c23-47d1-a43f-6edb1c3ed90b",
  "totalParticipacoes": 9,
  "totalEliminacoes": 8,
  "pontosAcumulados": 19,
  "mediaRank": "2989.56",
  "mediaEliminacoes": "0.89",
  "melhorRank": {
    "rank": 1061,
    "date": "2025-10-16"
  },
  "piorRank": {
    "rank": 4351,
    "date": "2025-10-19"
  },
  "historicoDeBatalhas": [
    {
      "date": "2025-10-13",
      "rank": 2150,
      "pontos": 3,
      "eliminatedCount": 0
    },
    {
      "date": "2025-10-14",
      "rank": 4249,
      "pontos": 0,
      "eliminatedCount": 0
    },
    {
      "date": "2025-10-15",
      "rank": 2579,
      "pontos": 3,
      "eliminatedCount": 4,
      "eliminatedBy": "davileitepereira172"
    },
    {
      "date": "2025-10-16",
      "rank": 1061,
      "pontos": 5,
      "eliminatedCount": 0,
      "eliminatedBy": "zick_alexandre"
    },
    {
      "date": "2025-10-17",
      "rank": 4058,
      "pontos": 0,
      "eliminatedCount": 1,
      "eliminatedBy": "augxsttzn__xzz"
    },
    {
      "date": "2025-10-18",
      "rank": 1739,
      "pontos": 5,
      "eliminatedCount": 2,
      "eliminatedBy": "crd._santos"
    },
    {
      "date": "2025-10-19",
      "rank": 4351,
      "pontos": 0,
      "eliminatedCount": 0,
      "eliminatedBy": "Desconhecido"
    },
    {
      "date": "2025-10-20",
      "rank": 2569,
      "pontos": 3,
      "eliminatedCount": 0,
      "eliminatedBy": "monaalise__7"
    },
    {
      "date": "2025-10-21",
      "rank": 4150,
      "pontos": 0,
      "eliminatedCount": 1,
      "eliminatedBy": "bernardoalves102142"
    }
  ]
}