{
  "username": "moniquebbarross",
  "imageUrl": "blob:null/14d84528-9f7a-451d-b009-9da223776232",
  "totalParticipacoes": 8,
  "totalEliminacoes": 5,
  "pontosAcumulados": 40,
  "mediaRank": "2159.63",
  "mediaEliminacoes": "0.63",
  "melhorRank": {
    "rank": 429,
    "date": "2025-10-15"
  },
  "piorRank": {
    "rank": 4423,
    "date": "2025-10-21"
  },
  "historicoDeBatalhas": [
    {
      "date": "2025-10-14",
      "rank": 1426,
      "pontos": 5,
      "eliminatedCount": 0
    },
    {
      "date": "2025-10-15",
      "rank": 429,
      "pontos": 15,
      "eliminatedCount": 2,
      "eliminatedBy": "luwxs.sk8"
    },
    {
      "date": "2025-10-16",
      "rank": 3159,
      "pontos": 1,
      "eliminatedCount": 0,
      "eliminatedBy": "kauan_gabriel12h"
    },
    {
      "date": "2025-10-17",
      "rank": 1573,
      "pontos": 5,
      "eliminatedCount": 2,
      "eliminatedBy": "pretinhoo_061"
    },
    {
      "date": "2025-10-18",
      "rank": 2012,
      "pontos": 3,
      "eliminatedCount": 0,
      "eliminatedBy": "saravelosodossantos80"
    },
    {
      "date": "2025-10-19",
      "rank": 3447,
      "pontos": 1,
      "eliminatedCount": 0,
      "eliminatedBy": "Desconhecido"
    },
    {
      "date": "2025-10-20",
      "rank": 808,
      "pontos": 10,
      "eliminatedCount": 1,
      "eliminatedBy": "vitorberlato6"
    },
    {
      "date": "2025-10-21",
      "rank": 4423,
      "pontos": 0,
      "eliminatedCount": 0,
      "eliminatedBy": "rocha_jnz"
    }
  ]
}