{
  "username": "murilo__096__",
  "imageUrl": "blob:null/daecfdbb-285e-48ef-ba35-79605910f5c2",
  "totalParticipacoes": 9,
  "totalEliminacoes": 4,
  "pontosAcumulados": 38,
  "mediaRank": "2342.33",
  "mediaEliminacoes": "0.44",
  "melhorRank": {
    "rank": 511,
    "date": "2025-10-21"
  },
  "piorRank": {
    "rank": 4180,
    "date": "2025-10-19"
  },
  "historicoDeBatalhas": [
    {
      "date": "2025-10-13",
      "rank": 751,
      "pontos": 10,
      "eliminatedCount": 0
    },
    {
      "date": "2025-10-14",
      "rank": 1344,
      "pontos": 5,
      "eliminatedCount": 0
    },
    {
      "date": "2025-10-15",
      "rank": 3807,
      "pontos": 1,
      "eliminatedCount": 0,
      "eliminatedBy": "oliveira_alexzz"
    },
    {
      "date": "2025-10-16",
      "rank": 3391,
      "pontos": 1,
      "eliminatedCount": 0,
      "eliminatedBy": "carlos8888.8888"
    },
    {
      "date": "2025-10-17",
      "rank": 2226,
      "pontos": 3,
      "eliminatedCount": 0,
      "eliminatedBy": "marcello4899"
    },
    {
      "date": "2025-10-18",
      "rank": 2887,
      "pontos": 3,
      "eliminatedCount": 2,
      "eliminatedBy": "kelvinsoccol"
    },
    {
      "date": "2025-10-19",
      "rank": 4180,
      "pontos": 0,
      "eliminatedCount": 0,
      "eliminatedBy": "Desconhecido"
    },
    {
      "date": "2025-10-20",
      "rank": 1984,
      "pontos": 5,
      "eliminatedCount": 2,
      "eliminatedBy": "gettjinx3d"
    },
    {
      "date": "2025-10-21",
      "rank": 511,
      "pontos": 10,
      "eliminatedCount": 0,
      "eliminatedBy": "evilynbeatriz244"
    }
  ]
}