{
  "username": "nascente_sofi90",
  "imageUrl": "blob:null/25b98da1-4fbb-484f-88db-d2fd30384940",
  "totalParticipacoes": 8,
  "totalEliminacoes": 5,
  "pontosAcumulados": 55,
  "mediaRank": "2006.75",
  "mediaEliminacoes": "0.63",
  "melhorRank": {
    "rank": 189,
    "date": "2025-10-21"
  },
  "piorRank": {
    "rank": 4284,
    "date": "2025-10-18"
  },
  "historicoDeBatalhas": [
    {
      "date": "2025-10-14",
      "rank": 718,
      "pontos": 10,
      "eliminatedCount": 0
    },
    {
      "date": "2025-10-15",
      "rank": 2275,
      "pontos": 3,
      "eliminatedCount": 2,
      "eliminatedBy": "maxwillianvillander_bjj"
    },
    {
      "date": "2025-10-16",
      "rank": 3570,
      "pontos": 1,
      "eliminatedCount": 0,
      "eliminatedBy": "melque920"
    },
    {
      "date": "2025-10-17",
      "rank": 2284,
      "pontos": 3,
      "eliminatedCount": 0,
      "eliminatedBy": "leleu_s1994"
    },
    {
      "date": "2025-10-18",
      "rank": 4284,
      "pontos": 0,
      "eliminatedCount": 2,
      "eliminatedBy": "allan_kracheski"
    },
    {
      "date": "2025-10-19",
      "rank": 2271,
      "pontos": 3,
      "eliminatedCount": 0,
      "eliminatedBy": "Desconhecido"
    },
    {
      "date": "2025-10-20",
      "rank": 463,
      "pontos": 15,
      "eliminatedCount": 1,
      "eliminatedBy": "itoshe675"
    },
    {
      "date": "2025-10-21",
      "rank": 189,
      "pontos": 20,
      "eliminatedCount": 0,
      "eliminatedBy": "naayaamorim"
    }
  ]
}