{
  "username": "pqp_oliver0dz9",
  "imageUrl": "blob:null/daf64bf8-ba9e-416e-ac20-e877aa156e8c",
  "totalParticipacoes": 9,
  "totalEliminacoes": 6,
  "pontosAcumulados": 31,
  "mediaRank": "2325.00",
  "mediaEliminacoes": "0.67",
  "melhorRank": {
    "rank": 1371,
    "date": "2025-10-15"
  },
  "piorRank": {
    "rank": 3796,
    "date": "2025-10-20"
  },
  "historicoDeBatalhas": [
    {
      "date": "2025-10-13",
      "rank": 3284,
      "pontos": 1,
      "eliminatedCount": 0
    },
    {
      "date": "2025-10-14",
      "rank": 2810,
      "pontos": 3,
      "eliminatedCount": 0
    },
    {
      "date": "2025-10-15",
      "rank": 1371,
      "pontos": 5,
      "eliminatedCount": 1,
      "eliminatedBy": "pedroytz01"
    },
    {
      "date": "2025-10-16",
      "rank": 1752,
      "pontos": 5,
      "eliminatedCount": 2,
      "eliminatedBy": "faelzinh.033"
    },
    {
      "date": "2025-10-17",
      "rank": 1503,
      "pontos": 5,
      "eliminatedCount": 1,
      "eliminatedBy": "_victtorcrf"
    },
    {
      "date": "2025-10-18",
      "rank": 1381,
      "pontos": 5,
      "eliminatedCount": 1,
      "eliminatedBy": "_kevin_sales"
    },
    {
      "date": "2025-10-19",
      "rank": 3157,
      "pontos": 1,
      "eliminatedCount": 0,
      "eliminatedBy": "Desconhecido"
    },
    {
      "date": "2025-10-20",
      "rank": 3796,
      "pontos": 1,
      "eliminatedCount": 1,
      "eliminatedBy": "geova.moraesferreira.5"
    },
    {
      "date": "2025-10-21",
      "rank": 1871,
      "pontos": 5,
      "eliminatedCount": 0,
      "eliminatedBy": "mayanny.rferreira"
    }
  ]
}