{
  "username": "pvd_santzbia",
  "imageUrl": "blob:null/73588a2c-b2f5-42a8-a3bf-de9e48e391d8",
  "totalParticipacoes": 9,
  "totalEliminacoes": 11,
  "pontosAcumulados": 76,
  "mediaRank": "2300.67",
  "mediaEliminacoes": "1.22",
  "melhorRank": {
    "rank": 41,
    "date": "2025-10-18"
  },
  "piorRank": {
    "rank": 4142,
    "date": "2025-10-20"
  },
  "historicoDeBatalhas": [
    {
      "date": "2025-10-13",
      "rank": 2831,
      "pontos": 3,
      "eliminatedCount": 0
    },
    {
      "date": "2025-10-14",
      "rank": 1686,
      "pontos": 5,
      "eliminatedCount": 0
    },
    {
      "date": "2025-10-15",
      "rank": 3889,
      "pontos": 1,
      "eliminatedCount": 0,
      "eliminatedBy": "eversonsssilva"
    },
    {
      "date": "2025-10-16",
      "rank": 2432,
      "pontos": 3,
      "eliminatedCount": 1,
      "eliminatedBy": "_telesjanjan"
    },
    {
      "date": "2025-10-17",
      "rank": 3025,
      "pontos": 1,
      "eliminatedCount": 0,
      "eliminatedBy": "neirafael.1234"
    },
    {
      "date": "2025-10-18",
      "rank": 41,
      "pontos": 40,
      "eliminatedCount": 5,
      "eliminatedBy": "vhlpz_"
    },
    {
      "date": "2025-10-19",
      "rank": 2527,
      "pontos": 3,
      "eliminatedCount": 0,
      "eliminatedBy": "Desconhecido"
    },
    {
      "date": "2025-10-20",
      "rank": 4142,
      "pontos": 0,
      "eliminatedCount": 2,
      "eliminatedBy": "taly.a589"
    },
    {
      "date": "2025-10-21",
      "rank": 133,
      "pontos": 20,
      "eliminatedCount": 3,
      "eliminatedBy": "megazznt"
    }
  ]
}