{
  "username": "roneyrichard477",
  "imageUrl": "blob:null/efe75266-024d-4a2e-bd4e-b146990f8eae",
  "totalParticipacoes": 9,
  "totalEliminacoes": 1,
  "pontosAcumulados": 49,
  "mediaRank": "2106.67",
  "mediaEliminacoes": "0.11",
  "melhorRank": {
    "rank": 588,
    "date": "2025-10-19"
  },
  "piorRank": {
    "rank": 4082,
    "date": "2025-10-15"
  },
  "historicoDeBatalhas": [
    {
      "date": "2025-10-13",
      "rank": 660,
      "pontos": 10,
      "eliminatedCount": 0
    },
    {
      "date": "2025-10-14",
      "rank": 948,
      "pontos": 10,
      "eliminatedCount": 0
    },
    {
      "date": "2025-10-15",
      "rank": 4082,
      "pontos": 0,
      "eliminatedCount": 0,
      "eliminatedBy": "capi_artx123"
    },
    {
      "date": "2025-10-16",
      "rank": 2734,
      "pontos": 3,
      "eliminatedCount": 0,
      "eliminatedBy": "gabriel_b._bowen"
    },
    {
      "date": "2025-10-17",
      "rank": 3838,
      "pontos": 1,
      "eliminatedCount": 1,
      "eliminatedBy": "jonas_17y"
    },
    {
      "date": "2025-10-18",
      "rank": 4037,
      "pontos": 0,
      "eliminatedCount": 0,
      "eliminatedBy": "talles_rdgss"
    },
    {
      "date": "2025-10-19",
      "rank": 588,
      "pontos": 10,
      "eliminatedCount": 0,
      "eliminatedBy": "Desconhecido"
    },
    {
      "date": "2025-10-20",
      "rank": 836,
      "pontos": 10,
      "eliminatedCount": 0,
      "eliminatedBy": "leosesilvahotmailcom"
    },
    {
      "date": "2025-10-21",
      "rank": 1237,
      "pontos": 5,
      "eliminatedCount": 0,
      "eliminatedBy": "erick_dannylo"
    }
  ]
}