{
  "username": "ruancassiano10",
  "imageUrl": "blob:null/65a9586a-cd0c-43ea-907a-d40f05d1d5a8",
  "totalParticipacoes": 9,
  "totalEliminacoes": 6,
  "pontosAcumulados": 64,
  "mediaRank": "2451.44",
  "mediaEliminacoes": "0.67",
  "melhorRank": {
    "rank": 14,
    "date": "2025-10-19"
  },
  "piorRank": {
    "rank": 4303,
    "date": "2025-10-20"
  },
  "historicoDeBatalhas": [
    {
      "date": "2025-10-13",
      "rank": 3074,
      "pontos": 1,
      "eliminatedCount": 0
    },
    {
      "date": "2025-10-14",
      "rank": 2421,
      "pontos": 3,
      "eliminatedCount": 0
    },
    {
      "date": "2025-10-15",
      "rank": 940,
      "pontos": 10,
      "eliminatedCount": 2,
      "eliminatedBy": "jose_pedromarinho"
    },
    {
      "date": "2025-10-16",
      "rank": 2793,
      "pontos": 3,
      "eliminatedCount": 1,
      "eliminatedBy": "dvs_07__"
    },
    {
      "date": "2025-10-17",
      "rank": 1493,
      "pontos": 5,
      "eliminatedCount": 2,
      "eliminatedBy": "021_pretoh_dell4"
    },
    {
      "date": "2025-10-18",
      "rank": 3874,
      "pontos": 1,
      "eliminatedCount": 0,
      "eliminatedBy": "camillatorresmeireles"
    },
    {
      "date": "2025-10-19",
      "rank": 14,
      "pontos": 40,
      "eliminatedCount": 0,
      "eliminatedBy": "Desconhecido"
    },
    {
      "date": "2025-10-20",
      "rank": 4303,
      "pontos": 0,
      "eliminatedCount": 1,
      "eliminatedBy": "carlos._.maciell"
    },
    {
      "date": "2025-10-21",
      "rank": 3151,
      "pontos": 1,
      "eliminatedCount": 0,
      "eliminatedBy": "adrianosilvasousa60"
    }
  ]
}