{
  "username": "sant_chaell",
  "imageUrl": "blob:null/8f405077-1aef-4d8d-b353-38b65b0b2553",
  "totalParticipacoes": 9,
  "totalEliminacoes": 7,
  "pontosAcumulados": 46,
  "mediaRank": "1762.33",
  "mediaEliminacoes": "0.78",
  "melhorRank": {
    "rank": 966,
    "date": "2025-10-17"
  },
  "piorRank": {
    "rank": 2685,
    "date": "2025-10-15"
  },
  "historicoDeBatalhas": [
    {
      "date": "2025-10-13",
      "rank": 1581,
      "pontos": 5,
      "eliminatedCount": 0
    },
    {
      "date": "2025-10-14",
      "rank": 1563,
      "pontos": 5,
      "eliminatedCount": 0
    },
    {
      "date": "2025-10-15",
      "rank": 2685,
      "pontos": 3,
      "eliminatedCount": 1,
      "eliminatedBy": "ary_x075"
    },
    {
      "date": "2025-10-16",
      "rank": 1956,
      "pontos": 5,
      "eliminatedCount": 2,
      "eliminatedBy": "silva.m7xz"
    },
    {
      "date": "2025-10-17",
      "rank": 966,
      "pontos": 10,
      "eliminatedCount": 2,
      "eliminatedBy": "vegetti_payet"
    },
    {
      "date": "2025-10-18",
      "rank": 1444,
      "pontos": 5,
      "eliminatedCount": 1,
      "eliminatedBy": "miguel_snttss"
    },
    {
      "date": "2025-10-19",
      "rank": 1210,
      "pontos": 5,
      "eliminatedCount": 0,
      "eliminatedBy": "Desconhecido"
    },
    {
      "date": "2025-10-20",
      "rank": 2483,
      "pontos": 3,
      "eliminatedCount": 0,
      "eliminatedBy": "x.joao_21"
    },
    {
      "date": "2025-10-21",
      "rank": 1973,
      "pontos": 5,
      "eliminatedCount": 1,
      "eliminatedBy": "jota_fdesouza"
    }
  ]
}