{
  "username": "tamymarks",
  "imageUrl": "blob:null/4001cf82-b806-425c-afe5-c1f164b872cf",
  "totalParticipacoes": 9,
  "totalEliminacoes": 11,
  "pontosAcumulados": 60,
  "mediaRank": "1578.89",
  "mediaEliminacoes": "1.22",
  "melhorRank": {
    "rank": 102,
    "date": "2025-10-16"
  },
  "piorRank": {
    "rank": 2787,
    "date": "2025-10-21"
  },
  "historicoDeBatalhas": [
    {
      "date": "2025-10-13",
      "rank": 2080,
      "pontos": 3,
      "eliminatedCount": 0
    },
    {
      "date": "2025-10-14",
      "rank": 2140,
      "pontos": 3,
      "eliminatedCount": 0
    },
    {
      "date": "2025-10-15",
      "rank": 809,
      "pontos": 10,
      "eliminatedCount": 2,
      "eliminatedBy": "wender1950"
    },
    {
      "date": "2025-10-16",
      "rank": 102,
      "pontos": 20,
      "eliminatedCount": 2,
      "eliminatedBy": "_thzini.zx"
    },
    {
      "date": "2025-10-17",
      "rank": 1079,
      "pontos": 5,
      "eliminatedCount": 0,
      "eliminatedBy": "costadavi751"
    },
    {
      "date": "2025-10-18",
      "rank": 2033,
      "pontos": 3,
      "eliminatedCount": 3,
      "eliminatedBy": "matheuseduardo4661"
    },
    {
      "date": "2025-10-19",
      "rank": 2374,
      "pontos": 3,
      "eliminatedCount": 0,
      "eliminatedBy": "Desconhecido"
    },
    {
      "date": "2025-10-20",
      "rank": 806,
      "pontos": 10,
      "eliminatedCount": 2,
      "eliminatedBy": "murillonani"
    },
    {
      "date": "2025-10-21",
      "rank": 2787,
      "pontos": 3,
      "eliminatedCount": 2,
      "eliminatedBy": "hamiltonteodorofilhodiogo"
    }
  ]
}