{
  "username": "thay_kauan14",
  "imageUrl": "blob:null/6c96bd19-a773-436b-a381-ec6393e4db27",
  "totalParticipacoes": 9,
  "totalEliminacoes": 8,
  "pontosAcumulados": 40,
  "mediaRank": "2185.78",
  "mediaEliminacoes": "0.89",
  "melhorRank": {
    "rank": 491,
    "date": "2025-10-14"
  },
  "piorRank": {
    "rank": 4125,
    "date": "2025-10-20"
  },
  "historicoDeBatalhas": [
    {
      "date": "2025-10-13",
      "rank": 3531,
      "pontos": 1,
      "eliminatedCount": 0
    },
    {
      "date": "2025-10-14",
      "rank": 491,
      "pontos": 15,
      "eliminatedCount": 0
    },
    {
      "date": "2025-10-15",
      "rank": 2290,
      "pontos": 3,
      "eliminatedCount": 1,
      "eliminatedBy": "marquesalex216"
    },
    {
      "date": "2025-10-16",
      "rank": 2475,
      "pontos": 3,
      "eliminatedCount": 1,
      "eliminatedBy": "valdenize_batista"
    },
    {
      "date": "2025-10-17",
      "rank": 1037,
      "pontos": 5,
      "eliminatedCount": 3,
      "eliminatedBy": "gab.nascc"
    },
    {
      "date": "2025-10-18",
      "rank": 2784,
      "pontos": 3,
      "eliminatedCount": 0,
      "eliminatedBy": "mmanuzzinha"
    },
    {
      "date": "2025-10-19",
      "rank": 1642,
      "pontos": 5,
      "eliminatedCount": 0,
      "eliminatedBy": "Desconhecido"
    },
    {
      "date": "2025-10-20",
      "rank": 4125,
      "pontos": 0,
      "eliminatedCount": 0,
      "eliminatedBy": "wesleyturockcavalcante"
    },
    {
      "date": "2025-10-21",
      "rank": 1297,
      "pontos": 5,
      "eliminatedCount": 3,
      "eliminatedBy": "antonio_carlos_mariosa2025"
    }
  ]
}