{
  "username": "vine.caval",
  "imageUrl": "blob:null/c4c48183-a700-464e-857c-4667a51c8385",
  "totalParticipacoes": 9,
  "totalEliminacoes": 5,
  "pontosAcumulados": 41,
  "mediaRank": "2583.44",
  "mediaEliminacoes": "0.56",
  "melhorRank": {
    "rank": 149,
    "date": "2025-10-17"
  },
  "piorRank": {
    "rank": 4289,
    "date": "2025-10-16"
  },
  "historicoDeBatalhas": [
    {
      "date": "2025-10-13",
      "rank": 845,
      "pontos": 10,
      "eliminatedCount": 0
    },
    {
      "date": "2025-10-14",
      "rank": 2780,
      "pontos": 3,
      "eliminatedCount": 0
    },
    {
      "date": "2025-10-15",
      "rank": 4054,
      "pontos": 0,
      "eliminatedCount": 1,
      "eliminatedBy": "eo_ricardo_0"
    },
    {
      "date": "2025-10-16",
      "rank": 4289,
      "pontos": 0,
      "eliminatedCount": 1,
      "eliminatedBy": "ycaro_gk1"
    },
    {
      "date": "2025-10-17",
      "rank": 149,
      "pontos": 20,
      "eliminatedCount": 2,
      "eliminatedBy": "arthu_rduartte62"
    },
    {
      "date": "2025-10-18",
      "rank": 3407,
      "pontos": 1,
      "eliminatedCount": 0,
      "eliminatedBy": "_lanzinhokj"
    },
    {
      "date": "2025-10-19",
      "rank": 1001,
      "pontos": 5,
      "eliminatedCount": 0,
      "eliminatedBy": "Desconhecido"
    },
    {
      "date": "2025-10-20",
      "rank": 3532,
      "pontos": 1,
      "eliminatedCount": 0,
      "eliminatedBy": "vito.gabriel9744"
    },
    {
      "date": "2025-10-21",
      "rank": 3194,
      "pontos": 1,
      "eliminatedCount": 1,
      "eliminatedBy": "_m.artinssz.l"
    }
  ]
}