{
  "username": "vini_loiola_",
  "imageUrl": "blob:null/0a64617c-6a59-4439-98de-d23d2c2cfbfb",
  "totalParticipacoes": 9,
  "totalEliminacoes": 10,
  "pontosAcumulados": 88,
  "mediaRank": "1717.78",
  "mediaEliminacoes": "1.11",
  "melhorRank": {
    "rank": 29,
    "date": "2025-10-13"
  },
  "piorRank": {
    "rank": 3376,
    "date": "2025-10-14"
  },
  "historicoDeBatalhas": [
    {
      "date": "2025-10-13",
      "rank": 29,
      "pontos": 40,
      "eliminatedCount": 0
    },
    {
      "date": "2025-10-14",
      "rank": 3376,
      "pontos": 1,
      "eliminatedCount": 0
    },
    {
      "date": "2025-10-15",
      "rank": 2264,
      "pontos": 3,
      "eliminatedCount": 1,
      "eliminatedBy": "mirellyminanda"
    },
    {
      "date": "2025-10-16",
      "rank": 2395,
      "pontos": 3,
      "eliminatedCount": 2,
      "eliminatedBy": "an.gellk"
    },
    {
      "date": "2025-10-17",
      "rank": 2903,
      "pontos": 3,
      "eliminatedCount": 4,
      "eliminatedBy": "_lukinhah"
    },
    {
      "date": "2025-10-18",
      "rank": 597,
      "pontos": 10,
      "eliminatedCount": 2,
      "eliminatedBy": "1olii_ver"
    },
    {
      "date": "2025-10-19",
      "rank": 2307,
      "pontos": 3,
      "eliminatedCount": 0,
      "eliminatedBy": "Desconhecido"
    },
    {
      "date": "2025-10-20",
      "rank": 229,
      "pontos": 20,
      "eliminatedCount": 1,
      "eliminatedBy": "lorrane.valeska"
    },
    {
      "date": "2025-10-21",
      "rank": 1360,
      "pontos": 5,
      "eliminatedCount": 0,
      "eliminatedBy": "thurznx.07"
    }
  ]
}