{
  "username": "vinny.10_",
  "imageUrl": "blob:null/32896624-7de8-4057-9d1a-e25269d2f93d",
  "totalParticipacoes": 8,
  "totalEliminacoes": 4,
  "pontosAcumulados": 48,
  "mediaRank": "2719.38",
  "mediaEliminacoes": "0.50",
  "melhorRank": {
    "rank": 110,
    "date": "2025-10-20"
  },
  "piorRank": {
    "rank": 4573,
    "date": "2025-10-19"
  },
  "historicoDeBatalhas": [
    {
      "date": "2025-10-14",
      "rank": 155,
      "pontos": 20,
      "eliminatedCount": 0
    },
    {
      "date": "2025-10-15",
      "rank": 3408,
      "pontos": 1,
      "eliminatedCount": 0,
      "eliminatedBy": "weweretooclosetothestars01"
    },
    {
      "date": "2025-10-16",
      "rank": 2859,
      "pontos": 3,
      "eliminatedCount": 1,
      "eliminatedBy": "caio_luaan"
    },
    {
      "date": "2025-10-17",
      "rank": 2491,
      "pontos": 3,
      "eliminatedCount": 0,
      "eliminatedBy": "gabrielroma94"
    },
    {
      "date": "2025-10-18",
      "rank": 4350,
      "pontos": 0,
      "eliminatedCount": 0,
      "eliminatedBy": "lauren.priuli.b"
    },
    {
      "date": "2025-10-19",
      "rank": 4573,
      "pontos": 0,
      "eliminatedCount": 0,
      "eliminatedBy": "Desconhecido"
    },
    {
      "date": "2025-10-20",
      "rank": 110,
      "pontos": 20,
      "eliminatedCount": 3,
      "eliminatedBy": "01ricardinn"
    },
    {
      "date": "2025-10-21",
      "rank": 3809,
      "pontos": 1,
      "eliminatedCount": 0,
      "eliminatedBy": "085_miguel_csc"
    }
  ]
}